{
  "totalRecord": {"num": "52"},
  "school":  [
    {
      "schoolid": "62",
      "schoolname": "郑州大学",
      "clicks": "11643087",
      "monthclicks": "170970",
      "weekclicks": "1114",
      "province": "河南",
      "schooltype": "普通本科",
      "schoolproperty": "综合类",
      "edudirectly": "0",
      "f985": "0",
      "f211": "1",
      "level": "本科",
      "autonomyrs": "1",
      "library": "714",
      "membership": "河南省人民政府",
      "schoolnature": "公办",
      "shoufei": "经有关部门批准，普通本科文科类专业学费3400元/生·年，理工类及体育类专业3700元/生·年，医学类专业4500元/生·年，艺术类专业5700元/生",
      "jianjie": "郑州大学(简称郑大，英文简称：ZZU)是国家“211工程”重点建设高校、国家“中西部高校提升综合实力计划”入选高校、河南省人民政府与教育部共建",
      "schoolcode": "412000100",
      "ranking": "19",
      "rankingCollegetype": "14",
      "guanwang": "http://www.zzu.edu.cn",
      "oldname": "郑州大学",
      "ads": "0",
      "center": "0",
      "master": "223",
      "num": "13815",
      "firstrate": "一流大学建设高校",
      "firstrateclass": []
    },
    {
      "schoolid": "463",
      "schoolname": "河南理工大学",
      "clicks": "7065963",
      "monthclicks": "157758",
      "weekclicks": "455",
      "province": "河南",
      "schooltype": "普通本科",
      "schoolproperty": "理工类",
      "edudirectly": "0",
      "f985": "0",
      "f211": "0",
      "level": "本科",
      "autonomyrs": "0",
      "library": "580",
      "membership": "河南省人民政府",
      "schoolnature": "公办",
      "shoufei": "招生计划、学费标准严格按照教育部和上级主管部门核准执行，详见考生所在省份招生部门《招生专业目录》、本校《招生简章》，或登录学校招生信息网查询。",
      "jianjie": "●中央与地方共建、以地方管理为主的河南省属重点高校●国家“中西部高校基础能力建设工程”重点建设高校●河南省人民政府",
      "schoolcode": "412000400",
      "ranking": "69",
      "rankingCollegetype": "25",
      "guanwang": "http://www.hpu.edu.cn/",
      "oldname": "河南理工大学  曾用名：焦作工学院",
      "ads": "1",
      "center": "0",
      "master": "119",
      "num": "7740",
      "firstrate": "其它",
      "firstrateclass": []
    },
    {
      "schoolid": "458",
      "schoolname": "郑州轻工业学院",
      "clicks": "4704975",
      "monthclicks": "112944",
      "weekclicks": "403",
      "province": "河南",
      "schooltype": "普通本科",
      "schoolproperty": "理工类",
      "edudirectly": "0",
      "f985": "0",
      "f211": "0",
      "level": "本科",
      "autonomyrs": "0",
      "library": "216",
      "membership": "河南省人民政府",
      "schoolnature": "公办",
      "shoufei": "第二十五条学费和住宿费标准东风校区和科学校区：普通本科文科类专业3400元/生/年，理工类及体育类专业3700元/生/年，普通艺术类专业5700元/生/年;中外合",
      "jianjie": "郑州轻工业学院（ZhengzhouUniversityofLightIndustry）位于河南省会郑州市，是河南省重点建设高校。建校以来",
      "schoolcode": "412000900",
      "ranking": "167",
      "rankingCollegetype": "80",
      "guanwang": "http://www.zzuli.edu.cn",
      "oldname": "郑州轻工业学院",
      "ads": "1",
      "center": "0",
      "master": "65",
      "num": "5467",
      "firstrate": "其它",
      "firstrateclass": []
    },
    {
      "schoolid": "466",
      "schoolname": "河南工业大学",
      "clicks": "4900238",
      "monthclicks": "142591",
      "weekclicks": "422",
      "province": "河南",
      "schooltype": "普通本科",
      "schoolproperty": "理工类",
      "edudirectly": "0",
      "f985": "0",
      "f211": "0",
      "level": "本科",
      "autonomyrs": "0",
      "library": "224",
      "membership": "河南省教育厅",
      "schoolnature": "公办",
      "shoufei": [],
      "jianjie": "河南工业大学是一所有62年办学历史，以工学为主，工学、理学、经济学、管理学、法学、文学、艺术学和农学等多学科协调发展，具有学士、硕士、博士三级人才培养体系的多科性大学。现有全日制普通高等教育",
      "schoolcode": "412000500",
      "ranking": "162",
      "rankingCollegetype": "76",
      "guanwang": "http://www.haut.edu.cn/",
      "oldname": "河南工业大学",
      "ads": "1",
      "center": "0",
      "master": "113",
      "num": "7074",
      "firstrate": "其它",
      "firstrateclass": []
    },
    {
      "schoolid": "460",
      "schoolname": "河南科技大学",
      "clicks": "7467939",
      "monthclicks": "172333",
      "weekclicks": "588",
      "province": "河南",
      "schooltype": "普通本科",
      "schoolproperty": "综合类",
      "edudirectly": "0",
      "f985": "0",
      "f211": "0",
      "level": "本科",
      "autonomyrs": "0",
      "library": "364",
      "membership": "河南省人民政府",
      "schoolnature": "公办",
      "shoufei": "五、收费标准及奖助学措施1.我校录取新生除软件工程专业外实行学分制学费管理，学分制学费由专业注册费和学分学费二部分组成，收费标准按照河南省发展和改革委员会审批的标准",
      "jianjie": "河南科技大学(简称河科大，英文简称：HAUST)是河南省人民政府与国家国防科工局共建高校、国家中西部高校基础能力建设工程支持高校、国家教育部本科教学工作水平评估优秀高校，是河南省重点建设的三",
      "schoolcode": "412000300",
      "ranking": "57",
      "rankingCollegetype": "725",
      "guanwang": "http://www.haust.edu.cn",
      "oldname": "河南科技大学  曾用名：洛阳工学院",
      "ads": "1",
      "center": "0",
      "master": "156",
      "num": "5122",
      "firstrate": "其它",
      "firstrateclass": []
    },
    {
      "schoolid": "481",
      "schoolname": "中原工学院",
      "clicks": "3826576",
      "monthclicks": "131896",
      "weekclicks": "311",
      "province": "河南",
      "schooltype": "普通本科",
      "schoolproperty": "理工类",
      "edudirectly": "0",
      "f985": "0",
      "f211": "0",
      "level": "本科",
      "autonomyrs": "0",
      "library": "415",
      "membership": "河南省人民政府",
      "schoolnature": "公办",
      "shoufei": "第二十五条学费按河南省物价部门审定标准执行，具体如下：文史类本科各专业学费为3400元/生·年;理工类本科各专业学费为3700元/生·年;艺术类本科各专业学费为5",
      "jianjie": "中原工学院是一所以工为主，纺织服装及相关学科特色鲜明，工、管、文、理、经、法、哲、史、艺等多学科协调发展的高水平教学型公办大学。学校始建于1955年，原名郑州纺织工学院，隶属于中华人民共和国",
      "schoolcode": "412001300",
      "ranking": "239",
      "rankingCollegetype": "104",
      "guanwang": "http://www.zzti.edu.cn/",
      "oldname": "中原工学院",
      "ads": "1",
      "center": "0",
      "master": "41",
      "num": "4884",
      "firstrate": "其它",
      "firstrateclass": []
    },
    {
      "schoolid": "462",
      "schoolname": "河南农业大学",
      "clicks": "3519385",
      "monthclicks": "82196",
      "weekclicks": "227",
      "province": "河南",
      "schooltype": "普通本科",
      "schoolproperty": "农林类",
      "edudirectly": "0",
      "f985": "0",
      "f211": "0",
      "level": "本科",
      "autonomyrs": "0",
      "library": "250",
      "membership": "河南省人民政府",
      "schoolnature": "公办",
      "shoufei": "第八章收费标准第一条普通本科专业理工类3700元/生·年，文史类3400元/生·年;第二条艺术类570",
      "jianjie": "筚路蓝缕，栉风沐雨，河南农业大学走过了百余年的办学历程。学校源自1902年创办的河南大学堂，先后经历了河南高等学堂、河南高等学校、河南公立农业专门学校、国立第五中山",
      "schoolcode": "412000600",
      "ranking": "273",
      "rankingCollegetype": "13",
      "guanwang": "http://zs.henau.edu.cn/",
      "oldname": "河南农业大学",
      "ads": "1",
      "center": "0",
      "master": "85",
      "num": "4998",
      "firstrate": "其它",
      "firstrateclass": []
    },
    {
      "schoolid": "883",
      "schoolname": "河南科技学院",
      "clicks": "2863852",
      "monthclicks": "90655",
      "weekclicks": "152",
      "province": "河南",
      "schooltype": "普通本科",
      "schoolproperty": "综合类",
      "edudirectly": "0",
      "f985": "0",
      "f211": "0",
      "level": "本科",
      "autonomyrs": "0",
      "library": "271",
      "membership": "河南省教育厅",
      "schoolnature": "公办",
      "shoufei": "第六章收费标准及其它第三十七条学校严格执行河南省教育厅、河南省发展和改革委员会、河南省财政厅批准的学费标准。具体为：(一)本科文科类",
      "jianjie": "河南科技学院是一所省属普通本科院校。学校始建于1939年，前身为中国共产党早期创建的延安自然科学院大学部生物系，历经北方大学农学院、华北大学农学院、华北大学农学院长治分院、北京农业大学长治分",
      "schoolcode": "412003000",
      "ranking": "329",
      "rankingCollegetype": "800",
      "guanwang": "http://www.hist.edu.cn",
      "oldname": "河南科技学院",
      "ads": "0",
      "center": "0",
      "master": "21",
      "num": "3192",
      "firstrate": "其它",
      "firstrateclass": []
    },
    {
      "schoolid": "3073",
      "schoolname": "河南牧业经济学院",
      "clicks": "625028",
      "monthclicks": "95741",
      "weekclicks": "205",
      "province": "河南",
      "schooltype": "普通本科",
      "schoolproperty": "财经类",
      "edudirectly": "0",
      "f985": "0",
      "f211": "0",
      "level": "本科",
      "autonomyrs": "0",
      "library": "242",
      "membership": "河南省人民政府",
      "schoolnature": "公办",
      "shoufei": "第二十五条各专业学费根据国家规定，学生入学须交纳学费、住宿费及其它相关费用。学校按河南省物价部门核定的收费标准对学生收取学费、住宿费及其它相关费用。考生可以在学校",
      "jianjie": "河南牧业经济学院是在原郑州牧业工程高等专科学校和原河南商业高等专科学校的基础上合并组建的一所省属公办全日制普通本科院校，是河南省本科转型发展试点学校。学校坐落于九州之中、中华腹地的河南省省会",
      "schoolcode": "412011500",
      "ranking": "1476",
      "rankingCollegetype": "490",
      "guanwang": "http://www.hnuahe.edu.cn",
      "oldname": "河南牧业经济学院  曾用名：郑州牧业工程高等专科学校/河南商业高等专科学校",
      "ads": "0",
      "center": "0",
      "master": "0",
      "num": "2564",
      "firstrate": "其它",
      "firstrateclass": []
    },
    {
      "schoolid": "873",
      "schoolname": "河南中医药大学",
      "clicks": "2703914",
      "monthclicks": "103389",
      "weekclicks": "270",
      "province": "河南",
      "schooltype": "普通本科",
      "schoolproperty": "医药类",
      "edudirectly": "0",
      "f985": "0",
      "f211": "0",
      "level": "本科",
      "autonomyrs": "0",
      "library": "157",
      "membership": "河南省教育厅",
      "schoolnature": "公办",
      "shoufei": "第六章收费标准及其他第二十二条根据国家有关规定，学生入学时必须按学校规定的缴费方式和时间缴纳学费、住宿费。经河南省物价局、财政厅和教育厅批准，2016年学费收费",
      "jianjie": "第二章学校概况第五条学校全称：河南中医药大学，国标代码10471。河南中医药大学创建于1958年，是教育部批准的具有高等学历教育招生资",
      "schoolcode": "412001800",
      "ranking": "390",
      "rankingCollegetype": "23",
      "guanwang": "http://www.hactcm.edu.cn",
      "oldname": "河南中医药大学  曾用名：河南中医学院",
      "ads": "1",
      "center": "0",
      "master": "53",
      "num": "4323",
      "firstrate": "其它",
      "firstrateclass": []
    },
    {
      "schoolid": "482",
      "schoolname": "新乡医学院",
      "clicks": "2833506",
      "monthclicks": "71777",
      "weekclicks": "272",
      "province": "河南",
      "schooltype": "普通本科",
      "schoolproperty": "医药类",
      "edudirectly": "0",
      "f985": "0",
      "f211": "0",
      "level": "本科",
      "autonomyrs": "0",
      "library": "115",
      "membership": "河南省教育厅",
      "schoolnature": "公办",
      "shoufei": "第五章收费标准第十八条文管类专业学费3400元/生·年，理工类专业学费3700元/生·年，医学类专业学费4500元/生·",
      "jianjie": "新乡医学院位于河南省新乡市，是目前河南省唯一独立建制的省属西医本科院校。学校渊源可追溯到1896年英国人劳海德在古城卫辉开办的西医诊所，医学教育肇始于1922年惠民医院护士学校，招收四年制护",
      "schoolcode": "412001900",
      "ranking": "395",
      "rankingCollegetype": "24",
      "guanwang": "http://www.xxmu.edu.cn/",
      "oldname": "新乡医学院",
      "ads": "0",
      "center": "0",
      "master": "54",
      "num": "2249",
      "firstrate": "其它",
      "firstrateclass": []
    },
    {
      "schoolid": "459",
      "schoolname": "河南大学",
      "clicks": "7703708",
      "monthclicks": "141509",
      "weekclicks": "608",
      "province": "河南",
      "schooltype": "普通本科",
      "schoolproperty": "综合类",
      "edudirectly": "0",
      "f985": "0",
      "f211": "0",
      "level": "本科",
      "autonomyrs": "0",
      "library": "750",
      "membership": "河南省人民政府",
      "schoolnature": "公办",
      "shoufei": "第二十三条河南大学各专业学费标准按豫财[2007]74号文件规定标准执行。我校各类专业具体学费标准如下：文史类3400元/生·年，理工类3700元/生·年，医学类4",
      "jianjie": "河南大学坐落在历史文化名城、八朝古都开封。这里曾是河南贡院的所在地，1903、1904年最后两场全国会试在这里举行，上千年的科举制度在这里划上句号。1912年，以林伯襄为代表的一批河南仁人先",
      "schoolcode": "412000200",
      "ranking": "67",
      "rankingCollegetype": "34",
      "guanwang": "http://www.henu.edu.cn/",
      "oldname": "河南大学",
      "ads": "1",
      "center": "0",
      "master": "260",
      "num": "5263",
      "firstrate": "一流学科建设高校",
      "firstrateclass": []
    },
    {
      "schoolid": "833",
      "schoolname": "河南师范大学",
      "clicks": "4183291",
      "monthclicks": "110925",
      "weekclicks": "352",
      "province": "河南",
      "schooltype": "普通本科",
      "schoolproperty": "师范类",
      "edudirectly": "0",
      "f985": "0",
      "f211": "0",
      "level": "本科",
      "autonomyrs": "0",
      "library": "500",
      "membership": "河南省教育厅",
      "schoolnature": "公办",
      "shoufei": "第二十六条收费标准：执行河南省发展改革委员会下达的《收费许可证》(20140253)和河南省财政厅豫教财[2007]74号文件中规定的收费项目和标准。如有新的文件按照新的文件执行。",
      "jianjie": "河南师范大学北依巍巍太行，南滨滚滚黄河，位于郑洛新国家自主创新示范区新乡片区—河南省新乡市，坐落在广袤的牧野大地、美丽的卫水之滨。河南师范大学的前身是创建于1923年的中州大学(",
      "schoolcode": "412000700",
      "ranking": "235",
      "rankingCollegetype": "15",
      "guanwang": "http://www.htu.cn",
      "oldname": "河南师范大学",
      "ads": "1",
      "center": "0",
      "master": "42",
      "num": "8808",
      "firstrate": "其它",
      "firstrateclass": []
    },
    {
      "schoolid": "876",
      "schoolname": "信阳师范学院",
      "clicks": "2839267",
      "monthclicks": "107810",
      "weekclicks": "206",
      "province": "河南",
      "schooltype": "普通本科",
      "schoolproperty": "师范类",
      "edudirectly": "0",
      "f985": "0",
      "f211": "0",
      "level": "本科",
      "autonomyrs": "0",
      "library": "191",
      "membership": "河南省人民政府",
      "schoolnature": "公办",
      "shoufei": "第七章收费标准第十七条新生收费项目分为学费、住宿费两类。住宿费为每生每年500-900元(由学校统一安排);学费按专业不同进行收费，具体专业收费标准按各省(区、",
      "jianjie": "信阳师范学院所在地——信阳市，位于河南省南部，东邻安徽，南接湖北，是江淮河汉间的战略要地，鄂豫皖区域性中心城市。山水秀丽，气候宜人，素有“北国江南，江南北",
      "schoolcode": "412002000",
      "ranking": "364",
      "rankingCollegetype": "29",
      "guanwang": "http://www.xytc.edu.cn",
      "oldname": "信阳师范学院",
      "ads": "1",
      "center": "0",
      "master": "81",
      "num": "4305",
      "firstrate": "其它",
      "firstrateclass": []
    },
    {
      "schoolid": "485",
      "schoolname": "周口师范学院",
      "clicks": "1498985",
      "monthclicks": "69246",
      "weekclicks": "278",
      "province": "河南",
      "schooltype": "普通本科",
      "schoolproperty": "师范类",
      "edudirectly": "0",
      "f985": "0",
      "f211": "0",
      "level": "本科",
      "autonomyrs": "0",
      "library": "145",
      "membership": "河南省教育厅",
      "schoolnature": "公办",
      "shoufei": "第六章费用奖助学金勤工助学等情况第二十一条：：我校各专业严格按照河南省发展和改革委员会、河南省财政厅、河南省教育厅联合下发的豫发改办[2004]232号文件规定",
      "jianjie": "周口师范学院是河南省属普通本科高校，地处三皇故都、老子故里、陈楚旧地、历史文化名城周口市。周口历史悠久，文化灿烂，人杰地灵，素有“华夏先驱，九州圣迹”之誉。颍河、沙河",
      "schoolcode": "412002100",
      "ranking": "667",
      "rankingCollegetype": "77",
      "guanwang": "http://www.zknu.edu.cn",
      "oldname": "周口师范学院",
      "ads": "0",
      "center": "0",
      "master": "4",
      "num": "3262",
      "firstrate": "其它",
      "firstrateclass": []
    },
    {
      "schoolid": "878",
      "schoolname": "安阳师范学院",
      "clicks": "2267795",
      "monthclicks": "89672",
      "weekclicks": "220",
      "province": "河南",
      "schooltype": "普通本科",
      "schoolproperty": "师范类",
      "edudirectly": "0",
      "f985": "0",
      "f211": "0",
      "level": "本科",
      "autonomyrs": "0",
      "library": "202",
      "membership": "河南省人民政府",
      "schoolnature": "公办",
      "shoufei": "我校新生收费标准严格按照河南省教育厅和物价局的有关文件精神执行。具体收费标准见《安阳师范学院2016年新生入学须知》。",
      "jianjie": "安阳师范学院位于甲骨文故乡、殷墟所在地、周易文化发祥地、红旗渠精神诞生地、国家历史文化名城、中国八大古都之一的安阳市，是河南省省属普通本科高校。学校前身是始建于1908年的彰德府安阳师范传习",
      "schoolcode": "412002400",
      "ranking": "466",
      "rankingCollegetype": "43",
      "guanwang": "http://www.aynu.edu.cn/",
      "oldname": "安阳师范学院",
      "ads": "1",
      "center": "0",
      "master": "1",
      "num": "2913",
      "firstrate": "其它",
      "firstrateclass": []
    },
    {
      "schoolid": "493",
      "schoolname": "许昌学院",
      "clicks": "1648973",
      "monthclicks": "80833",
      "weekclicks": "223",
      "province": "河南",
      "schooltype": "普通本科",
      "schoolproperty": "理工类",
      "edudirectly": "0",
      "f985": "0",
      "f211": "0",
      "level": "本科",
      "autonomyrs": "0",
      "library": "195",
      "membership": "河南省教育厅",
      "schoolnature": "公办",
      "shoufei": "第十五条学费标准：按照教育部和上级主管部门核准执行。学校各类专业学费标准如下：普通本科专业：文科3400元/生·学年，理科",
      "jianjie": "许昌学院是一所省属全日制普通本科院校。学校坐落于汉魏故都——河南省许昌市。许昌地处中原腹地，既是一座历史悠久的文化名城，又是一座蓬勃发展的现代新城。许昌三国文化底蕴深",
      "schoolcode": "412003100",
      "ranking": "615",
      "rankingCollegetype": "923",
      "guanwang": "http://www.xcu.edu.cn",
      "oldname": "许昌学院",
      "ads": "1",
      "center": "0",
      "master": "0",
      "num": "3476",
      "firstrate": "其它",
      "firstrateclass": []
    },
    {
      "schoolid": "487",
      "schoolname": "南阳师范学院",
      "clicks": "2064167",
      "monthclicks": "113899",
      "weekclicks": "273",
      "province": "河南",
      "schooltype": "普通本科",
      "schoolproperty": "师范类",
      "edudirectly": "0",
      "f985": "0",
      "f211": "0",
      "level": "本科",
      "autonomyrs": "0",
      "library": "139",
      "membership": "河南省人民政府",
      "schoolnature": "公办",
      "shoufei": "一、国家奖学金由中央政府出资设立，用于奖励在校期间表现特别优秀的学生。国家奖学金每年评选一次，奖励标准为每人每年8000元。二、国家励志奖学金",
      "jianjie": "南阳师范学院是河南省省属全日制普通本科高等院校，办学历史可追溯到1907年，有着深厚的文化底蕴和优良的办学传统，已形成了师范教育和非师范教育并存、特色鲜明、优势互补、协调发展的办学格局。2007",
      "schoolcode": "412002200",
      "ranking": "513",
      "rankingCollegetype": "51",
      "guanwang": "http://www.nynu.edu.cn",
      "oldname": "南阳师范学院",
      "ads": "1",
      "center": "0",
      "master": "2",
      "num": "3549",
      "firstrate": "其它",
      "firstrateclass": []
    },
    {
      "schoolid": "484",
      "schoolname": "洛阳师范学院",
      "clicks": "2990705",
      "monthclicks": "112494",
      "weekclicks": "288",
      "province": "河南",
      "schooltype": "普通本科",
      "schoolproperty": "综合类",
      "edudirectly": "0",
      "f985": "0",
      "f211": "0",
      "level": "本科",
      "autonomyrs": "0",
      "library": "225",
      "membership": "河南省人民政府",
      "schoolnature": "公办",
      "shoufei": "第二十一条收费标准新生收费项目分为学费、住宿费两类。住宿费为800-1100元/生·学年(由学校统一安排);各专业学费标准按河南省发改委批准的标准执",
      "jianjie": "洛阳师范学院是一所省属普通高等师范本科院校，位于千年帝都、牡丹花城——洛阳，文脉传承，底蕴丰厚。学校北依洛河，碧水东流，杨柳堆烟，流传着洛神宓妃的美丽传说;西望关林和",
      "schoolcode": "412002300",
      "ranking": "347",
      "rankingCollegetype": "801",
      "guanwang": "http://www.lynu.cn",
      "oldname": "洛阳师范学院",
      "ads": "1",
      "center": "0",
      "master": "7",
      "num": "3594",
      "firstrate": "其它",
      "firstrateclass": []
    },
    {
      "schoolid": "489",
      "schoolname": "商丘师范学院",
      "clicks": "2597733",
      "monthclicks": "92032",
      "weekclicks": "296",
      "province": "河南",
      "schooltype": "普通本科",
      "schoolproperty": "师范类",
      "edudirectly": "0",
      "f985": "0",
      "f211": "0",
      "level": "本科",
      "autonomyrs": "0",
      "library": "163",
      "membership": "河南省人民政府",
      "schoolnature": "公办",
      "shoufei": [],
      "jianjie": "商丘师范学院坐落于国家级历史文化名城、三商之源、华商之都——河南省商丘市，北依风景优美的黄河故道国家森林公园;南望历史上人文荟萃的归",
      "schoolcode": "412002500",
      "ranking": "389",
      "rankingCollegetype": "33",
      "guanwang": "http://www.sqnc.edu.cn/",
      "oldname": "商丘师范学院",
      "ads": "1",
      "center": "0",
      "master": "0",
      "num": "3815",
      "firstrate": "其它",
      "firstrateclass": []
    },
    {
      "schoolid": "490",
      "schoolname": "河南财经政法大学",
      "clicks": "6259154",
      "monthclicks": "155919",
      "weekclicks": "537",
      "province": "河南",
      "schooltype": "普通本科",
      "schoolproperty": "财经类",
      "edudirectly": "0",
      "f985": "0",
      "f211": "0",
      "level": "本科",
      "autonomyrs": "0",
      "library": "812",
      "membership": "河南省人民政府",
      "schoolnature": "公办",
      "shoufei": "第十九条学费标准为：普通类专科及对口升学3300元/生·年;普通类本科3400元/生·年。除学费外，还要按标准收取住宿费，生活费用自理。如国家及省政策有所变动，最终",
      "jianjie": "学校概况河南财经政法大学位于河南省郑州市，地处中华腹地，九州通衢，北邻黄河，西依嵩山。学校由原河南财经学院和原河南省政法管理干部学院于2010年3月合并组建而成，是",
      "schoolcode": "412002600",
      "ranking": "101",
      "rankingCollegetype": "10",
      "guanwang": "http://www.huel.edu.cn",
      "oldname": "河南财经政法大学  曾用名：河南财经学院",
      "ads": "1",
      "center": "0",
      "master": "55",
      "num": "3903",
      "firstrate": "其它",
      "firstrateclass": []
    },
    {
      "schoolid": "479",
      "schoolname": "郑州航空工业管理学院",
      "clicks": "4243954",
      "monthclicks": "95089",
      "weekclicks": "306",
      "province": "河南",
      "schooltype": "普通本科",
      "schoolproperty": "财经类",
      "edudirectly": "0",
      "f985": "0",
      "f211": "0",
      "level": "本科",
      "autonomyrs": "0",
      "library": "184",
      "membership": "河南省人民政府",
      "schoolnature": "公办",
      "shoufei": "第六章学费标准及奖贷助情况第十六条本科专业学费标准。普通本科专业：会计学、会计学(注册会计师方向)、审计学、财务管理、旅游管理、工商管",
      "jianjie": "郑州航空工业管理学院是一所全日制普通本科院校，其前身是1949年成立的平原省财经学校，后几经更名和迁址，1964年在全国16所航空学校专业调整合并时，更名为郑州航空工业学校。1978年升格为",
      "schoolcode": "412001200",
      "ranking": "191",
      "rankingCollegetype": "24",
      "guanwang": "http://www.zua.edu.cn/",
      "oldname": "郑州航空工业管理学院",
      "ads": "1",
      "center": "0",
      "master": "11",
      "num": "8133",
      "firstrate": "其它",
      "firstrateclass": []
    },
    {
      "schoolid": "884",
      "schoolname": "黄淮学院",
      "clicks": "1708749",
      "monthclicks": "80206",
      "weekclicks": "171",
      "province": "河南",
      "schooltype": "普通本科",
      "schoolproperty": "综合类",
      "edudirectly": "0",
      "f985": "0",
      "f211": "0",
      "level": "本科",
      "autonomyrs": "0",
      "library": "268",
      "membership": "河南省教育厅",
      "schoolnature": "公办",
      "shoufei": "第十九条我校各专业严格按河南省发展和改革委员会、河南省财政厅、河南省教育厅联合下发的豫发改办〔2004〕232号文件规定的标准收取学费。",
      "jianjie": "黄淮学院是2004年经教育部批准升格的一所全日制普通本科高校，具有43年的办学历史。是教育部应用技术大学改革战略研究试点院校、中国应用技术大学联盟副理事长单位、河南省首批示范性应用技术类型本科院",
      "schoolcode": "412002800",
      "ranking": "570",
      "rankingCollegetype": "141",
      "guanwang": "http://www.huanghuai.edu.cn",
      "oldname": "黄淮学院",
      "ads": "1",
      "center": "0",
      "master": "0",
      "num": "2396",
      "firstrate": "其它",
      "firstrateclass": []
    },
    {
      "schoolid": "880",
      "schoolname": "平顶山学院",
      "clicks": "1372645",
      "monthclicks": "71402",
      "weekclicks": "183",
      "province": "河南",
      "schooltype": "普通本科",
      "schoolproperty": "综合类",
      "edudirectly": "0",
      "f985": "0",
      "f211": "0",
      "level": "本科",
      "autonomyrs": "0",
      "library": "162",
      "membership": "河南省教育厅",
      "schoolnature": "公办",
      "shoufei": "第五章新生入学及其他第二十条学费按河南省物价部门审定标准执行，具体如下：文史类本科各专业学费为3400元/生•年，文史类专科各专业学费为3300元/生",
      "jianjie": "平顶山学院：百舸争流竞中原(国标代码:10919)在豫招生代码：普通本专科6125专升本6126中外课程合作6127软件类6128",
      "schoolcode": "412002700",
      "ranking": "672",
      "rankingCollegetype": "729",
      "guanwang": "http://www.pdsu.edu.cn",
      "oldname": "平顶山学院",
      "ads": "0",
      "center": "0",
      "master": "0",
      "num": "792",
      "firstrate": "其它",
      "firstrateclass": []
    },
    {
      "schoolid": "1178",
      "schoolname": "洛阳理工学院",
      "clicks": "3773058",
      "monthclicks": "116118",
      "weekclicks": "252",
      "province": "河南",
      "schooltype": "普通本科",
      "schoolproperty": "理工类",
      "edudirectly": "0",
      "f985": "0",
      "f211": "0",
      "level": "本科",
      "autonomyrs": "0",
      "library": "273",
      "membership": "河南省人民政府",
      "schoolnature": "公办",
      "shoufei": "普通类：文史类本科(含文理兼收专业)每人每年3400元，理工类本科每人每年3700元;文史类专科(含文理兼收专业)每人每年3300元，理工类专科每人每年3600元;艺术类本科每人每年5700",
      "jianjie": "洛阳理工学院是省属全日制普通本科院校,坐落于首批国家历史文化名城、被誉为“千年帝都，牡丹花城”的十三朝古都、中原经济区副中心城市—洛阳。",
      "schoolcode": "412001700",
      "ranking": "242",
      "rankingCollegetype": "105",
      "guanwang": "http://www.lit.edu.cn",
      "oldname": "洛阳理工学院  曾用名：洛阳工业高等专科学校/洛阳大学",
      "ads": "1",
      "center": "0",
      "master": "0",
      "num": "3845",
      "firstrate": "其它",
      "firstrateclass": []
    },
    {
      "schoolid": "1919",
      "schoolname": "新乡学院",
      "clicks": "1732806",
      "monthclicks": "93651",
      "weekclicks": "368",
      "province": "河南",
      "schooltype": "普通本科",
      "schoolproperty": "师范类",
      "edudirectly": "0",
      "f985": "0",
      "f211": "0",
      "level": "本科",
      "autonomyrs": "0",
      "library": "146",
      "membership": "河南省教育厅",
      "schoolnature": "公办",
      "shoufei": "六、收费标准1.学费：本科：文科专业3400元/年·生，理科专业3700元/年·生，艺术类专业5700元/年",
      "jianjie": "学校名片¶全国高等教育满意度调查，居河南参评高校第一¶全国第一个本科层次3D打印人才培养高校",
      "schoolcode": "412002900",
      "ranking": "583",
      "rankingCollegetype": "61",
      "guanwang": "http://www.xxu.edu.cn",
      "oldname": "新乡学院  曾用名：新乡师范高等专科学校/平原大学/新乡教育学院",
      "ads": "1",
      "center": "0",
      "master": "0",
      "num": "2905",
      "firstrate": "其它",
      "firstrateclass": []
    },
    {
      "schoolid": "894",
      "schoolname": "河南工学院",
      "clicks": "2045859",
      "monthclicks": "99760",
      "weekclicks": "154",
      "province": "河南",
      "schooltype": "普通本科",
      "schoolproperty": "理工类",
      "edudirectly": "0",
      "f985": "0",
      "f211": "0",
      "level": "本科",
      "autonomyrs": "0",
      "library": "119",
      "membership": "河南省人民政府",
      "schoolnature": "公办",
      "shoufei": "第五章培养费用第十六条学校按照河南省教育厅、财政厅和物价局规定标准收取下列费用：(一)培养费：文史类本科各",
      "jianjie": "河南工学院始建于1975年，是教育部批准设立的省属公办普通本科高校，是全国就业先进工作单位和全国毕业生就业50强高校。学校位于郑洛新国家自主创新示范区、中原城市群核心区重要城市、豫北工业名城",
      "schoolcode": "412003500",
      "ranking": "457",
      "rankingCollegetype": "172",
      "guanwang": "http://www.hneeu.edu.cn",
      "oldname": "河南工学院  曾用名：河南机电高等专科学校",
      "ads": "0",
      "center": "0",
      "master": "0",
      "num": "--",
      "firstrate": "其它",
      "firstrateclass": []
    },
    {
      "schoolid": "834",
      "schoolname": "安阳工学院",
      "clicks": "1867366",
      "monthclicks": "116268",
      "weekclicks": "202",
      "province": "河南",
      "schooltype": "普通本科",
      "schoolproperty": "理工类",
      "edudirectly": "0",
      "f985": "0",
      "f211": "0",
      "level": "本科",
      "autonomyrs": "0",
      "library": "151",
      "membership": "河南省人民政府",
      "schoolnature": "公办",
      "shoufei": [],
      "jianjie": "欢迎报考安阳工学院学校代码：6135、6136、6137安阳工学院坐落于历史文化名城、中国八大古都之一的河南省安阳市。安阳位于晋冀豫交汇处",
      "schoolcode": "412001500",
      "ranking": "536",
      "rankingCollegetype": "190",
      "guanwang": "http://www.ayit.edu.cn",
      "oldname": "安阳工学院",
      "ads": "1",
      "center": "0",
      "master": "0",
      "num": "3380",
      "firstrate": "其它",
      "firstrateclass": []
    },
    {
      "schoolid": "1323",
      "schoolname": "河南工程学院",
      "clicks": "3683516",
      "monthclicks": "86514",
      "weekclicks": "125",
      "province": "河南",
      "schooltype": "普通本科",
      "schoolproperty": "理工类",
      "edudirectly": "0",
      "f985": "0",
      "f211": "0",
      "level": "本科",
      "autonomyrs": "0",
      "library": "220",
      "membership": "河南省人民政府",
      "schoolnature": "公办",
      "shoufei": "第六章学费和住宿费标准第二十五条1、本科专业学费：艺术类5700元/年•生，理工类3700元/年•生，文史类3400元/年•生。/",
      "jianjie": "河南工程学院是2007年3月经国家教育部和河南省人民政府批准设立的一所普通公办本科高校。学院具有五十多年的办学历史。多年来学院依托两大传统支柱产业——煤炭行业和纺织行业，紧",
      "schoolcode": "412001000",
      "ranking": "222",
      "rankingCollegetype": "99",
      "guanwang": "http://www.haue.edu.cn",
      "oldname": "河南工程学院  曾用名：郑州经济管理干部学院/河南纺织高等专科学校",
      "ads": "0",
      "center": "0",
      "master": "0",
      "num": "3342",
      "firstrate": "其它",
      "firstrateclass": []
    },
    {
      "schoolid": "1920",
      "schoolname": "河南财政金融学院",
      "clicks": "621941",
      "monthclicks": "116396",
      "weekclicks": "137",
      "province": "河南",
      "schooltype": "普通本科",
      "schoolproperty": "财经类",
      "edudirectly": "0",
      "f985": "0",
      "f211": "0",
      "level": "本科",
      "autonomyrs": "0",
      "library": "109",
      "membership": "河南省教育厅",
      "schoolnature": "公办",
      "shoufei": "第十八条学校收费标准严格按照政府有关部门批准的收费标准执行。学费和住宿费等参见本校的《招生简章》或考生所在省份《招生专业目录》。旅游英语(航空服务英语方向)、汽车",
      "jianjie": "河南财政税务高等专科学校位于河南省会郑州，其前身是始建于1963年的河南省会计学校，1985年6月经河南省人民政府批准，组建成立河南省财政税务专科学校，1992年更名为河南财政税务高等专科学",
      "schoolcode": "412004400",
      "ranking": "1198",
      "rankingCollegetype": "112",
      "guanwang": "http://www.hacz.edu.cn",
      "oldname": "河南财政金融学院  曾用名：河南财政税务高等专科学校",
      "ads": "0",
      "center": "0",
      "master": "0",
      "num": "--",
      "firstrate": "其它",
      "firstrateclass": []
    }
  ]
}