{
  "totalRecord": {"num": "24"},
  "school":  [
    {
      "schoolid": "59",
      "schoolname": "南开大学",
      "clicks": "9438663",
      "monthclicks": "41829",
      "weekclicks": "568",
      "province": "天津",
      "schooltype": "普通本科",
      "schoolproperty": "综合类",
      "edudirectly": "1",
      "f985": "1",
      "f211": "1",
      "level": "本科",
      "autonomyrs": "1",
      "library": "361",
      "membership": "教育部",
      "schoolnature": "公办",
      "shoufei": "根据国家和天津市有关文件精神，本科各专业学费标准预定为：软件工程专业一、二年级5800元/年，三、四年级12000元/年;绘画专业15000元/年，视觉传达设计和环境设计专业12000元/年;城",
      "jianjie": "南开大学是国家教育部直属重点综合性大学，是敬爱的周恩来总理的母校。南开大学创建于1919年，创办人是近代著名爱国教育家严修和张伯苓。抗日战争时期，南开大学与北京大学、清华大学在昆",
      "schoolcode": "122000100",
      "ranking": "38",
      "rankingCollegetype": "25",
      "guanwang": "http://www.nankai.edu.cn/",
      "oldname": "南开大学",
      "ads": "0",
      "center": "0",
      "master": "231",
      "num": "3029",
      "firstrate": "一流大学建设高校",
      "firstrateclass": []
    },
    {
      "schoolid": "60",
      "schoolname": "天津大学",
      "clicks": "11286330",
      "monthclicks": "49741",
      "weekclicks": "520",
      "province": "天津",
      "schooltype": "普通本科",
      "schoolproperty": "理工类",
      "edudirectly": "1",
      "f985": "1",
      "f211": "1",
      "level": "本科",
      "autonomyrs": "1",
      "library": "263",
      "membership": "教育部",
      "schoolnature": "公办",
      "shoufei": "第十八条天津大学高职（专科）招生按我校相关招生简章进行，只招收天津理科生源且为走读生，学制3年，录取原则同本章程第四章，毕业后颁发天津大学专科毕业证书。第十九条",
      "jianjie": "天津大学是教育部直属国家重点大学，其前身为北洋大学，始建于1895年10月2日，是中国第一所现代大学，素以“实事求是”的校训、“严谨治学”的校风和",
      "schoolcode": "122000200",
      "ranking": "11",
      "rankingCollegetype": "3",
      "guanwang": "http://www.tju.edu.cn/",
      "oldname": "天津大学  曾用名：北洋大学",
      "ads": "0",
      "center": "0",
      "master": "178",
      "num": "2639",
      "firstrate": "一流大学建设高校",
      "firstrateclass": []
    },
    {
      "schoolid": "82",
      "schoolname": "天津科技大学",
      "clicks": "6761004",
      "monthclicks": "92373",
      "weekclicks": "781",
      "province": "天津",
      "schooltype": "普通本科",
      "schoolproperty": "理工类",
      "edudirectly": "0",
      "f985": "0",
      "f211": "0",
      "level": "本科",
      "autonomyrs": "0",
      "library": "254",
      "membership": "天津市教育委员会",
      "schoolnature": "公办",
      "shoufei": "第九条学费的收取标准为：文科类(不含外语类)专业4400元/生/年;理工、外语类专业5400元/生/年;设计学类专业12000元/生/年，表演、动画专业15000元/生/年;中日合作办学专",
      "jianjie": "天津科技大学是中央和地方共建、以天津市管理为主的公办全日制普通高等院校，是天津市重点建设的以工为主，工、理、文、农、医、经、管、法、艺等学科协调发展的多科性大学。学校创建于1958年，前身为",
      "schoolcode": "122000500",
      "ranking": "71",
      "rankingCollegetype": "27",
      "guanwang": "http://www.tust.edu.cn",
      "oldname": "天津科技大学",
      "ads": "1",
      "center": "0",
      "master": "74",
      "num": "3565",
      "firstrate": "其它",
      "firstrateclass": []
    },
    {
      "schoolid": "80",
      "schoolname": "天津工业大学",
      "clicks": "5857199",
      "monthclicks": "76836",
      "weekclicks": "540",
      "province": "天津",
      "schooltype": "普通本科",
      "schoolproperty": "理工类",
      "edudirectly": "0",
      "f985": "0",
      "f211": "0",
      "level": "本科",
      "autonomyrs": "0",
      "library": "213",
      "membership": "天津市教育委员会",
      "schoolnature": "公办",
      "shoufei": "第二十六条学费：文科类（不含外国语言文学类）4400元/生.年，理工外语类5400元/生.年，艺术设计学类12000元/生.年，戏剧与影视学类15000元/生.年；中外合",
      "jianjie": "天津工业大学简介天津工业大学是教育部与天津市共建、天津市重点建设的全日制普通高等学校，在教育部首轮本科教学评估中获得优秀。学校历史悠久，最早的系始建于1912年，现",
      "schoolcode": "122000400",
      "ranking": "117",
      "rankingCollegetype": "52",
      "guanwang": "http://www.tjpu.edu.cn/",
      "oldname": "天津工业大学",
      "ads": "1",
      "center": "0",
      "master": "44",
      "num": "3793",
      "firstrate": "一流学科建设高校",
      "firstrateclass": []
    },
    {
      "schoolid": "88",
      "schoolname": "中国民航大学",
      "clicks": "6506417",
      "monthclicks": "69335",
      "weekclicks": "866",
      "province": "天津",
      "schooltype": "普通本科",
      "schoolproperty": "理工类",
      "edudirectly": "0",
      "f985": "0",
      "f211": "0",
      "level": "本科",
      "autonomyrs": "0",
      "library": "0",
      "membership": "中国民用航空总局",
      "schoolnature": "公办",
      "shoufei": "第六章收费标准、奖助学金及其他第二十九条学校按照天津市发展和改革委员会、天津市财政局、天津市教育委员会批准的学费标准收费。本科每年学费5200-5800元;空中",
      "jianjie": "1．历史沿革中国民航大学是中国民用航空局直属的一所以培养高级工程技术和管理人才为主的普通高等学校。学校的前身是1951年9月成立的军委民航局第二民用航空学校。1958年12",
      "schoolcode": "122000300",
      "ranking": "87",
      "rankingCollegetype": "38",
      "guanwang": "http://www.cauc.edu.cn/zh/",
      "oldname": "中国民航大学  曾用名：中国民用航空学院",
      "ads": "1",
      "center": "1",
      "master": "62",
      "num": "3229",
      "firstrate": "其它",
      "firstrateclass": []
    },
    {
      "schoolid": "81",
      "schoolname": "天津理工大学",
      "clicks": "6795155",
      "monthclicks": "87762",
      "weekclicks": "862",
      "province": "天津",
      "schooltype": "普通本科",
      "schoolproperty": "理工类",
      "edudirectly": "0",
      "f985": "0",
      "f211": "0",
      "level": "本科",
      "autonomyrs": "0",
      "library": "165",
      "membership": "天津市教育委员会",
      "schoolnature": "公办",
      "shoufei": "本科学费标准：文科类(不含外国语言文学类)每生每学年4400元，理工、外语类每生每学年5400元，艺术设计学类每生每学年12000元，音乐与舞蹈学类、戏剧与影视学类、美术学类(摄影)每生每学",
      "jianjie": "天津理工大学是一所以工为主，工理结合，工、理、管、文、艺等学科协调发展的多科性大学。学校始建于1979年，前身为天津理工学院。1996年，与原天津大学分校、天津大学机电分校、天津大学冶金分校三所",
      "schoolcode": "122000600",
      "ranking": "77",
      "rankingCollegetype": "32",
      "guanwang": "http://www.tjut.edu.cn/",
      "oldname": "天津理工大学  曾用名：天津理工学院",
      "ads": "1",
      "center": "0",
      "master": "86",
      "num": "3995",
      "firstrate": "其它",
      "firstrateclass": []
    },
    {
      "schoolid": "93",
      "schoolname": "天津农学院",
      "clicks": "2108316",
      "monthclicks": "26143",
      "weekclicks": "312",
      "province": "天津",
      "schooltype": "普通本科",
      "schoolproperty": "农林类",
      "edudirectly": "0",
      "f985": "0",
      "f211": "0",
      "level": "本科",
      "autonomyrs": "0",
      "library": "67",
      "membership": "天津市教育委员会",
      "schoolnature": "公办",
      "shoufei": "学费标准：本科农学、经济学、管理学类专业每生每学年4400元;理工外语类专业每生每学年5400元;软件工程专业(天津市“3+1”教学模式示范专业)按照天津市发改委批准的示",
      "jianjie": "天津农学院始建于1976年。2002年经天津市政府批准，天津市城乡经济学校并入天津农学院。1982年获学士学位授予权，2006年获硕士学位授予权。1996年首批通过教育部本科教学合格评价，200",
      "schoolcode": "122001300",
      "ranking": "452",
      "rankingCollegetype": "25",
      "guanwang": "http://www.tjau.edu.cn/",
      "oldname": "天津农学院",
      "ads": "0",
      "center": "0",
      "master": "15",
      "num": "1888",
      "firstrate": "其它",
      "firstrateclass": []
    },
    {
      "schoolid": "78",
      "schoolname": "天津医科大学",
      "clicks": "4359668",
      "monthclicks": "36623",
      "weekclicks": "513",
      "province": "天津",
      "schooltype": "普通本科",
      "schoolproperty": "医药类",
      "edudirectly": "0",
      "f985": "0",
      "f211": "1",
      "level": "本科",
      "autonomyrs": "0",
      "library": "60",
      "membership": "天津市教育委员会",
      "schoolnature": "公办",
      "shoufei": "按照教育部《普通高等学校本科专业目录》规定的学科门类，文科类(不含外国语言文学类)：每生每学年4400元;理工外语类：每生每学年5400元;医学类：每生每学年5",
      "jianjie": "天津医科大学的前身天津医学院创建于1951年，是新中国成立后国家政务院批准新建的第一所高等医学院校，著名内分泌学家、医学教育家朱宪彝教授为首任校长。1993年，天津市委、市政府决定天津医学院与天津",
      "schoolcode": "122000700",
      "ranking": "217",
      "rankingCollegetype": "3",
      "guanwang": "http://www.tijmu.edu.cn/",
      "oldname": "天津医科大学",
      "ads": "0",
      "center": "0",
      "master": "68",
      "num": "550",
      "firstrate": "一流学科建设高校",
      "firstrateclass": []
    },
    {
      "schoolid": "89",
      "schoolname": "天津中医药大学",
      "clicks": "2796270",
      "monthclicks": "36087",
      "weekclicks": "477",
      "province": "天津",
      "schooltype": "普通本科",
      "schoolproperty": "医药类",
      "edudirectly": "0",
      "f985": "0",
      "f211": "0",
      "level": "本科",
      "autonomyrs": "0",
      "library": "162",
      "membership": "天津市教育委员会",
      "schoolnature": "公办",
      "shoufei": "学费收取按天津市规定的标准执行，文科类专业：4400元/生/年;理工外语类专业：5400元/生/年;医学类专业：5800元/生/年;中外合作办学临床药学专业：国内28000元/生/年，在英国",
      "jianjie": "天津中医药大学创建于1958年，是教育部高等学校中医学、医学人文素质教学指导委员会主任委员单位和世界中医药学会联合会教育指导委员会主任委员单位，是国家教育部批准的唯一一所中国传统医药国际学院",
      "schoolcode": "122000800",
      "ranking": "368",
      "rankingCollegetype": "19",
      "guanwang": "http://www.tjutcm.edu.cn",
      "oldname": "天津中医药大学",
      "ads": "1",
      "center": "0",
      "master": "25",
      "num": "1097",
      "firstrate": "一流学科建设高校",
      "firstrateclass": []
    },
    {
      "schoolid": "79",
      "schoolname": "天津师范大学",
      "clicks": "5879804",
      "monthclicks": "90887",
      "weekclicks": "876",
      "province": "天津",
      "schooltype": "普通本科",
      "schoolproperty": "师范类",
      "edudirectly": "0",
      "f985": "0",
      "f211": "0",
      "level": "本科",
      "autonomyrs": "0",
      "library": "200",
      "membership": "天津市教育委员会",
      "schoolnature": "公办",
      "shoufei": "现行本科学费标准：普通类专业为4400-5400元/生·年(软件工程专业按照天津市发改委批准的示范性软件学院收费标准执行);艺术类专业为12000-15000元/生middo",
      "jianjie": "天津师范大学是天津市属重点院校，始建于1958年，原名天津师范学院，1982年更名为天津师范大学。1999年4月，原天津师范大学、天津师范高等专科学校、天津教育学院合并组建新天津师范大学。",
      "schoolcode": "122000900",
      "ranking": "127",
      "rankingCollegetype": "4",
      "guanwang": "http://www.tjnu.edu.cn/",
      "oldname": "天津师范大学",
      "ads": "0",
      "center": "0",
      "master": "41",
      "num": "1609",
      "firstrate": "其它",
      "firstrateclass": []
    },
    {
      "schoolid": "90",
      "schoolname": "天津职业技术师范大学",
      "clicks": "2096322",
      "monthclicks": "38956",
      "weekclicks": "387",
      "province": "天津",
      "schooltype": "普通本科",
      "schoolproperty": "师范类",
      "edudirectly": "0",
      "f985": "0",
      "f211": "0",
      "level": "本科",
      "autonomyrs": "0",
      "library": "90",
      "membership": "天津市教育委员会",
      "schoolnature": "公办",
      "shoufei": "学费标准：艺术类本科专业学费12000～15000元/生·年;中外合作办学专业学费按照天津市物价局批准的收费标准执行;其它本科专业学费4400～5400元/生·年",
      "jianjie": "天津职业技术师范大学是我国最早建立的以培养职业教育师资为主要任务的普通高等师范院校，成立于1979年，隶属于原国家劳动部；2000年，转制为中央与地方共建，以天津市管理为主；2010年，更名为天",
      "schoolcode": "122001400",
      "ranking": "467",
      "rankingCollegetype": "44",
      "guanwang": "http://www.tute.edu.cn",
      "oldname": "天津职业技术师范大学  曾用名：天津职业技术师范学院、天津工程师范学院",
      "ads": "1",
      "center": "0",
      "master": "7",
      "num": "2480",
      "firstrate": "其它",
      "firstrateclass": []
    },
    {
      "schoolid": "87",
      "schoolname": "天津外国语大学",
      "clicks": "3919226",
      "monthclicks": "30055",
      "weekclicks": "402",
      "province": "天津",
      "schooltype": "普通本科",
      "schoolproperty": "语言类",
      "edudirectly": "0",
      "f985": "0",
      "f211": "0",
      "level": "本科",
      "autonomyrs": "0",
      "library": "120",
      "membership": "天津市教育委员会",
      "schoolnature": "公办",
      "shoufei": "学费收取按天津市规定的标准执行，文科类(不含外国语言文学类)专业：每生每学年4400元;理工外语类专业：每生每学年5400元;艺术类专业：每生每学年15000元。上述学费不包含学生自愿参加的特色",
      "jianjie": "天津外国语大学是一所以外国语言文学学科为优势学科，文学、经济学、管理学、法学、教育学、艺术学、工学等多学科协调发展、特色鲜明的高等学校，是全国最早独立设置的八所外语院校之一。19",
      "schoolcode": "122001500",
      "ranking": "227",
      "rankingCollegetype": "6",
      "guanwang": "http://www.tjfsu.edu.cn/",
      "oldname": "天津外国语大学  曾用名：天津外国语专科学校",
      "ads": "1",
      "center": "0",
      "master": "26",
      "num": "1706",
      "firstrate": "其它",
      "firstrateclass": []
    },
    {
      "schoolid": "85",
      "schoolname": "天津商业大学",
      "clicks": "6134082",
      "monthclicks": "54616",
      "weekclicks": "435",
      "province": "天津",
      "schooltype": "普通本科",
      "schoolproperty": "财经类",
      "edudirectly": "0",
      "f985": "0",
      "f211": "0",
      "level": "本科",
      "autonomyrs": "0",
      "library": "173",
      "membership": "天津市教育委员会",
      "schoolnature": "公办",
      "shoufei": "收费标准：文科类专业学费4400元/生、年;理工外语类专业学费5400元/生、年;设",
      "jianjie": "天津商业大学的前身是天津商学院，由国家商业部和天津市人民政府于1980年创建。1998年实行中央与地方共建、以地方管理为主的管理体制。2007年更名为天津商业大学。学校以建设商科特色鲜明、对",
      "schoolcode": "122001100",
      "ranking": "94",
      "rankingCollegetype": "9",
      "guanwang": "http://www.tjcu.edu.cn",
      "oldname": "天津商业大学",
      "ads": "1",
      "center": "0",
      "master": "24",
      "num": "3953",
      "firstrate": "其它",
      "firstrateclass": []
    },
    {
      "schoolid": "84",
      "schoolname": "天津财经大学",
      "clicks": "6159559",
      "monthclicks": "37748",
      "weekclicks": "543",
      "province": "天津",
      "schooltype": "普通本科",
      "schoolproperty": "财经类",
      "edudirectly": "0",
      "f985": "0",
      "f211": "0",
      "level": "本科",
      "autonomyrs": "0",
      "library": "90",
      "membership": "天津市教育委员会",
      "schoolnature": "公办",
      "shoufei": "学费标准:文科类每生每学年4400元;理工外语类每生每学年5400元;设计学类每生每学年12000元;美术学类每生每学年15000元;中外合作办学专业金融学(能源金融)每生每学年34000",
      "jianjie": "天津财经大学是新中国最早建立的财经大学之一，是一所以应用经济和工商管理学科为主干，兼有文学、法学、理学、工学、教育七大学科门类交叉渗透、协调发展的多科性大学。学校始建于",
      "schoolcode": "122001000",
      "ranking": "81",
      "rankingCollegetype": "6",
      "guanwang": "http://www.tjufe.edu.cn",
      "oldname": "天津财经大学",
      "ads": "1",
      "center": "0",
      "master": "24",
      "num": "1880",
      "firstrate": "其它",
      "firstrateclass": []
    },
    {
      "schoolid": "92",
      "schoolname": "天津体育学院",
      "clicks": "896953",
      "monthclicks": "9280",
      "weekclicks": "146",
      "province": "天津",
      "schooltype": "普通本科",
      "schoolproperty": "体育类",
      "edudirectly": "0",
      "f985": "0",
      "f211": "0",
      "level": "本科",
      "autonomyrs": "0",
      "library": "30",
      "membership": "天津市教育委员会",
      "schoolnature": "公办",
      "shoufei": "根据规定，学生入学须缴纳学费、住宿费及其他有关费用，学校按照政府制订的收费标准对学生收费。本科学费标准：文科类每生每学年4400元;理工外语类每生每学年5400元;医学类每生每学年5800元;舞",
      "jianjie": "津体育学院建立于1958年8月。当时，国家体委、教育部根据华北地区体育教育事业发展需要以及体育师资、竞技体育和体育管理人才匮乏的状况，决定在当时的河北省省会天津市组建天津体育学院，由当时的河",
      "schoolcode": "122001600",
      "ranking": "800",
      "rankingCollegetype": "3",
      "guanwang": "http://www.tjus.edu.cn",
      "oldname": "天津体育学院",
      "ads": "0",
      "center": "0",
      "master": "6",
      "num": "210",
      "firstrate": "其它",
      "firstrateclass": []
    },
    {
      "schoolid": "94",
      "schoolname": "天津音乐学院",
      "clicks": "250899",
      "monthclicks": "3970",
      "weekclicks": "81",
      "province": "天津",
      "schooltype": "普通本科",
      "schoolproperty": "艺术类",
      "edudirectly": "0",
      "f985": "0",
      "f211": "0",
      "level": "本科",
      "autonomyrs": "0",
      "library": "7",
      "membership": "天津市教育委员会",
      "schoolnature": "公办",
      "shoufei": "新生一律缴费上学，本科学费标准：艺术与科技专业12000元/学年，其他专业15000元/学年。学院实行奖学金制，对品学兼优学生进行奖励。家庭经济困难学生资助政策及有关程序，按照财政部教科文司",
      "jianjie": "天津音乐学院于一九五八年十月四日建院。发展和繁荣音乐文化事业，为两个文明建设做贡献是学院的办学宗旨。培养适应社会需要的德艺双馨的音乐理论、音乐创作、音乐表演专门人才和音乐师资是办学的中心任务",
      "schoolcode": "122001800",
      "ranking": "1472",
      "rankingCollegetype": "38",
      "guanwang": "http://www.tjcm.edu.cn/",
      "oldname": "天津音乐学院",
      "ads": "0",
      "center": "0",
      "master": "0",
      "num": "--",
      "firstrate": "其它",
      "firstrateclass": []
    },
    {
      "schoolid": "95",
      "schoolname": "天津美术学院",
      "clicks": "408690",
      "monthclicks": "5666",
      "weekclicks": "74",
      "province": "天津",
      "schooltype": "普通本科",
      "schoolproperty": "艺术类",
      "edudirectly": "0",
      "f985": "0",
      "f211": "0",
      "level": "本科",
      "autonomyrs": "0",
      "library": "20",
      "membership": "天津市教育委员会",
      "schoolnature": "公办",
      "shoufei": "按照天津市物价局批准的收费标准，艺术类专业收费标准为：艺术学理论类10000元/生.年，艺术设计",
      "jianjie": "天津美术学院座落在海河之滨、三叉河口，位于天津市中心。其前身为北洋女师范学堂，1906年6月由中国近代著名教育家傅增湘先生创办，是我国最早的公立高等学府之一。辛亥革命与qu",
      "schoolcode": "122001700",
      "ranking": "1171",
      "rankingCollegetype": "20",
      "guanwang": "http://www.tjarts.edu.cn",
      "oldname": "天津美术学院",
      "ads": "1",
      "center": "0",
      "master": "2",
      "num": "--",
      "firstrate": "其它",
      "firstrateclass": []
    },
    {
      "schoolid": "41",
      "schoolname": "河北工业大学",
      "clicks": "5436115",
      "monthclicks": "43364",
      "weekclicks": "403",
      "province": "天津",
      "schooltype": "普通本科",
      "schoolproperty": "理工类",
      "edudirectly": "0",
      "f985": "0",
      "f211": "1",
      "level": "本科",
      "autonomyrs": "0",
      "library": "102",
      "membership": "河北省教育厅",
      "schoolnature": "公办",
      "shoufei": "收费标准：普通本科专业学费5000元/人年;艺术类专业学费8750元/人年;双学位班专业学费5000元/人年，另外选修课程按学分收费，每学分100元;中外合作办学学费2",
      "jianjie": "河北工业大学是一所以工科为主，工、理、管、经、文、法多学科协调发展的河北省属骨干大学，是进入国家“211工程”重点建设的高校。学校坐落在沿海开放城市——天津市，分为北辰",
      "schoolcode": "132000200",
      "ranking": "138",
      "rankingCollegetype": "62",
      "guanwang": "http://www.hebut.edu.cn/",
      "oldname": "河北工业大学",
      "ads": "1",
      "center": "0",
      "master": "131",
      "num": "4613",
      "firstrate": "一流学科建设高校",
      "firstrateclass": []
    },
    {
      "schoolid": "2304",
      "schoolname": "天津天狮学院",
      "clicks": "830550",
      "monthclicks": "11172",
      "weekclicks": "188",
      "province": "天津",
      "schooltype": "普通本科",
      "schoolproperty": "综合类",
      "edudirectly": "0",
      "f985": "0",
      "f211": "0",
      "level": "本科",
      "autonomyrs": "0",
      "library": "34",
      "membership": "天津市教育委员会",
      "schoolnature": "民办",
      "shoufei": "学院严格执行天津市物价局批准的民办高校收费标准，高职生学费：普通类专业8000元/生·年，艺术类专业9500元/生·年;本科生学费：生物工程、计算机科学与技术、自动化",
      "jianjie": "天津天狮学院是由天津天狮集团有限公司投资兴办，于2008年4月经国家教育部批准成立的全日制民办普通本科高校。其前身为1999年7月教育部批准成立的天狮职业技术学院，目前是天津市唯一一所民办本",
      "schoolcode": "122005400",
      "ranking": "836",
      "rankingCollegetype": "220",
      "guanwang": "http://www.tianshi.edu.cn/",
      "oldname": "天津天狮学院",
      "ads": "0",
      "center": "0",
      "master": "0",
      "num": "1046",
      "firstrate": "其它",
      "firstrateclass": []
    },
    {
      "schoolid": "1211",
      "schoolname": "武警后勤学院",
      "clicks": "352632",
      "monthclicks": "1393",
      "weekclicks": "32",
      "province": "天津",
      "schooltype": "普通本科",
      "schoolproperty": "军事类",
      "edudirectly": "0",
      "f985": "0",
      "f211": "0",
      "level": "本科",
      "autonomyrs": "0",
      "library": "12",
      "membership": "武警后勤部",
      "schoolnature": "公办",
      "shoufei": [],
      "jianjie": "中国人民武装警察部队后勤学院是在中国人民武装警察部队医学院的主体基础上，武警工程学院后勤专业并入而成，是武警部队惟一的高等医学院校，编制为副军级，隶属武警部队后勤部。学院位于天津市河东区成林道，占",
      "schoolcode": "122005200",
      "ranking": "1264",
      "rankingCollegetype": "23",
      "guanwang": "http://www.wjyxy.com",
      "oldname": "武警后勤学院",
      "ads": "0",
      "center": "0",
      "master": "0",
      "num": "--",
      "firstrate": "其它",
      "firstrateclass": []
    },
    {
      "schoolid": "858",
      "schoolname": "天津中德应用技术大学",
      "clicks": "659895",
      "monthclicks": "31263",
      "weekclicks": "291",
      "province": "天津",
      "schooltype": "普通本科",
      "schoolproperty": "理工类",
      "edudirectly": "0",
      "f985": "0",
      "f211": "0",
      "level": "本科",
      "autonomyrs": "0",
      "library": "0",
      "membership": "天津市教育委员会",
      "schoolnature": "公办",
      "shoufei": "收费标准：学校执行国家有关规定。1.本科文科类每生每学年4400元;理工外语类每生每学年5400元;艺术学理论类每生每学年10000元，设计学类每生每学年12000元。",
      "jianjie": "天津中德应用技术大学是天津市属全日制公办高等院校，是中国与德国、日本、西班牙三国政府在职业教育和培训领域最大的合作项目，是国家示范性优秀建设高职院校，是全国职业教育先进单位。学校坐落在渤海之",
      "schoolcode": "121601",
      "ranking": "1130",
      "rankingCollegetype": "341",
      "guanwang": "http://www.tsguas.edu.cn",
      "oldname": "天津中德应用技术大学  曾用名：天津中德职业技术学院",
      "ads": "1",
      "center": "0",
      "master": "0",
      "num": "--",
      "firstrate": "其它",
      "firstrateclass": []
    },
    {
      "schoolid": "1253",
      "schoolname": "中国人民解放军军事交通学院",
      "clicks": "551623",
      "monthclicks": "982",
      "weekclicks": "11",
      "province": "天津",
      "schooltype": "普通本科",
      "schoolproperty": "军事类",
      "edudirectly": "0",
      "f985": "0",
      "f211": "0",
      "level": "本科",
      "autonomyrs": "0",
      "library": "0",
      "membership": "解放军总后勤部",
      "schoolnature": "公办",
      "shoufei": [],
      "jianjie": "军事交通学院隶属于解放军总后勤部，是全军培养军事交通运输、军用车辆装备和军用物资储运领域高层次人才的最高学府，是集保障指挥与工程技术于一体、多科性教学科研型军事院校，主要面向全军培养本科、硕",
      "schoolcode": "122005100",
      "ranking": "974",
      "rankingCollegetype": "15",
      "guanwang": "http://www.jjxy.cn",
      "oldname": "中国人民解放军军事交通学院",
      "ads": "0",
      "center": "0",
      "master": "0",
      "num": "--",
      "firstrate": "其它",
      "firstrateclass": []
    },
    {
      "schoolid": "2994",
      "schoolname": "武警指挥学院",
      "clicks": "136263",
      "monthclicks": "1156",
      "weekclicks": "29",
      "province": "天津",
      "schooltype": "普通本科",
      "schoolproperty": "军事类",
      "edudirectly": "0",
      "f985": "0",
      "f211": "0",
      "level": "本科",
      "autonomyrs": "0",
      "library": "0",
      "membership": "武警总部",
      "schoolnature": "公办",
      "shoufei": [],
      "jianjie": "中国人民武装警察部队指挥学院是一所为武警部队培养中高级指挥人才、高级理论人才、高级参谋人才和优秀师资人才的高等军事院校。是武警部队唯一的中级指挥院校，隶属中国人民武装警察部队总部，正军级。学院地址",
      "schoolcode": "122006000",
      "ranking": "2078",
      "rankingCollegetype": "38",
      "guanwang": [],
      "oldname": "武警指挥学院",
      "ads": "0",
      "center": "0",
      "master": "0",
      "num": "--",
      "firstrate": "其它",
      "firstrateclass": []
    },
    {
      "schoolid": "91",
      "schoolname": "天津城建大学",
      "clicks": "3353937",
      "monthclicks": "42490",
      "weekclicks": "328",
      "province": "天津",
      "schooltype": "普通本科",
      "schoolproperty": "综合类",
      "edudirectly": "0",
      "f985": "0",
      "f211": "0",
      "level": "本科",
      "autonomyrs": "0",
      "library": "75",
      "membership": "天津市教育委员会",
      "schoolnature": "公办",
      "shoufei": "1、各类专业学费：文科类每生每学年4400元;理工外语类每生每学年5400元;艺术学设计学类每生每学年12000元;软件专业的学生进入天津市大学软件学院学习，采用新的人才培养模式开设的相关专",
      "jianjie": "天津城建大学是一所天津市市属普通高等学校，始建于1978年，前身是天津大学建筑分校，1987年更名为天津城市建设学院，2013年更为现名。原全国政协主席李瑞环为学校题写了校名。建校30多年来，学",
      "schoolcode": "122001200",
      "ranking": "271",
      "rankingCollegetype": "68",
      "guanwang": "http://www.tcu.edu.cn",
      "oldname": "天津城建大学  曾用名：天津城市建设学院",
      "ads": "1",
      "center": "0",
      "master": "12",
      "num": "2607",
      "firstrate": "其它",
      "firstrateclass": []
    }
  ]
}